LICENSE
netflix/__init__.py
netflix/exceptions.py
netflix/models.py
netflix-0.1.1.dist-info/LICENSE
netflix-0.1.1.dist-info/WHEEL
netflix-0.1.1.dist-info/METADATA
netflix-0.1.1.dist-info/RECORD
