Metadata-Version: 2.1
Name: netflix
Version: 0.1.1
Summary: A Python client for Netflix.
Home-page: https://github.com/efe/netflix
License: Apache-2.0
Keywords: python,netflix,movie,tv-show
Author: Efe Öge
Author-email: efeoge@gmail.com
Requires-Python: >=2.7
Classifier: License :: OSI Approved :: Apache Software License
Classifier: Operating System :: OS Independent
Classifier: Programming Language :: Python
Classifier: Programming Language :: Python :: 2
Classifier: Programming Language :: Python :: 2.7
Classifier: Programming Language :: Python :: 3
Classifier: Programming Language :: Python :: 3.5
Classifier: Programming Language :: Python :: 3.6
Classifier: Programming Language :: Python :: 3.7
Classifier: Programming Language :: Python :: 3.8
Classifier: Topic :: Software Development :: Libraries :: Python Modules
Requires-Dist: beautifulsoup4 (>=4.0)
Requires-Dist: requests (>=2.0)
Project-URL: Repository, https://github.com/efe/netflix
